sdmn/__init__.py
sdmn/configuration.py
sdmn/display.py
sdmn/elements/__init__.py
sdmn/elements/network.py
sdmn/elements/service.py
sdmn/elements/volume.py
sdmn/environments.py
sdmn/sdmn.py
sdmn-0.1.2.dist-info/entry_points.txt
sdmn-0.1.2.dist-info/WHEEL
sdmn-0.1.2.dist-info/METADATA
sdmn-0.1.2.dist-info/RECORD
